mux21.v
module mux21 (
    input a, b, s,
    output y
);
    assign y = (s) ? b : a;
endmodule

comparator_8bit.v
module comparator_1bit (
    input a, b,
    output L, Eq, G
);

assign L  = ~a & b;
assign Eq = ~(a ^ b);   // XNOR for equality
assign G  = a & ~b;
    
endmodule

module comparator_8bit (
    input  [7:0] A,
    input  [7:0] B,
    output L, Eq, G
);

wire [7:0] Lw, Eqw, Gw;

comparator_1bit c0 (A[0], B[0], Lw[0], Eqw[0], Gw[0]);
comparator_1bit c1 (A[1], B[1], Lw[1], Eqw[1], Gw[1]);
comparator_1bit c2 (A[2], B[2], Lw[2], Eqw[2], Gw[2]);
comparator_1bit c3 (A[3], B[3], Lw[3], Eqw[3], Gw[3]);
comparator_1bit c4 (A[4], B[4], Lw[4], Eqw[4], Gw[4]);
comparator_1bit c5 (A[5], B[5], Lw[5], Eqw[5], Gw[5]);
comparator_1bit c6 (A[6], B[6], Lw[6], Eqw[6], Gw[6]);
comparator_1bit c7 (A[7], B[7], Lw[7], Eqw[7], Gw[7]);

assign Eq = &Eqw;

assign G =
    Gw[7] |
    (Eqw[7] & Gw[6]) |
    (Eqw[7] & Eqw[6] & Gw[5]) |
    (Eqw[7] & Eqw[6] & Eqw[5] & Gw[4]) |
    (Eqw[7] & Eqw[6] & Eqw[5] & Eqw[4] & Gw[3]) |
    (Eqw[7] & Eqw[6] & Eqw[5] & Eqw[4] & Eqw[3] & Gw[2]) |
    (Eqw[7] & Eqw[6] & Eqw[5] & Eqw[4] & Eqw[3] & Eqw[2] & Gw[1]) |
    (Eqw[7] & Eqw[6] & Eqw[5] & Eqw[4] & Eqw[3] & Eqw[2] & Eqw[1] & Gw[0]);

assign L =
    Lw[7] |
    (Eqw[7] & Lw[6]) |
    (Eqw[7] & Eqw[6] & Lw[5]) |
    (Eqw[7] & Eqw[6] & Eqw[5] & Lw[4]) |
    (Eqw[7] & Eqw[6] & Eqw[5] & Eqw[4] & Lw[3]) |
    (Eqw[7] & Eqw[6] & Eqw[5] & Eqw[4] & Eqw[3] & Lw[2]) |
    (Eqw[7] & Eqw[6] & Eqw[5] & Eqw[4] & Eqw[3] & Eqw[2] & Lw[1]) |
    (Eqw[7] & Eqw[6] & Eqw[5] & Eqw[4] & Eqw[3] & Eqw[2] & Eqw[1] & Lw[0]);

endmodule

dff_8bit.v
module dff_1bit (
    output reg q,
    input wire d,
    input wire clk,
    input wire rst_n
);

    always @(posedge clk or negedge rst_n) begin
        if (!rst_n) begin
            q <= 1'b0; // Active-low reset
        end else begin
            q <= d;    // On positive clock edge, q gets the value of d
        end
    end

endmodule

module dff_8bit (
    output wire [7:0] q,
    input  wire [7:0] d,
    input  wire clk,
    input  wire rst_n
);

genvar i;
generate
    for (i = 0; i < 8; i = i + 1) begin : dff_array
        dff_1bit dff_inst (
            .q(q[i]),
            .d(d[i]),
            .clk(clk),
            .rst_n(rst_n)
        );
    end
endgenerate

endmodule

adder_8bit.v
module half_adder (
    input a, b,
    output sum, carry
);
    assign sum = a ^ b;
    assign carry = a & b;
endmodule

module full_adder (
    input a, b, cin,
    output sum, cout 
);
    wire s1, c1, c2;

    half_adder ha1(.a(a), .b(b), .sum(s1), .carry(c1));
    half_adder ha2(.a(s1), .b(cin), .sum(sum), .carry(c2));

    assign cout = c1 | c2;
endmodule

module adder_8bit (
    input [7:0] a, b,
    input cin,
    output [7:0] sum,
    output cout
);
    wire [8:0] c;
    assign c[0] = cin;
    assign cout = c[8];

    genvar i;
    generate
        for (i = 0; i < 8; i = i + 1) begin : gen_adders
            full_adder fa (
                .a(a[i]), 
                .b(b[i]), 
                .cin(c[i]), 
                .sum(sum[i]), 
                .cout(c[i+1])
            );
        end
    endgenerate
endmodule

pwm.v
module pwm_8bit (
    input  wire        clk,
    input  wire        rst_n,
    input  wire [7:0]  dutyCycle,
    output wire        pwm_out
);

wire [7:0] counter;
wire [7:0] next_counter;
wire cout_dummy;

wire L, Eq, G;

// --------------------
// 1️⃣ 8-bit Adder (counter + 1)
// --------------------
adder_8bit adder_inst (
    .a(counter),
    .b(8'b00000001),
    .cin(1'b0),
    .sum(next_counter),
    .cout(cout_dummy)
);

// --------------------
// 2️⃣ 8-bit Register (Counter Storage)
// --------------------
dff_8bit counter_reg (
    .q(counter),
    .d(next_counter),
    .clk(clk),
    .rst_n(rst_n)
);

// --------------------
// 3️⃣ Comparator (counter vs dutyCycle)
// --------------------
comparator_8bit comp_inst (
    .A(counter),
    .B(dutyCycle),
    .L(L),
    .Eq(Eq),
    .G(G)
);

// --------------------
// 4️⃣ MUX to Generate PWM
// If counter < dutyCycle → output 1
// --------------------
mux21 pwm_mux (
    .a(1'b0),
    .b(1'b1),
    .s(L),
    .y(pwm_out)
);

endmodule

tb_pwm.v
`timescale 1ns/1ps

module tb_pwm;

reg clk;
reg rst_n;
reg [7:0] dutyCycle;
wire pwm_out;

// Instantiate DUT
pwm_8bit uut (
    .clk(clk),
    .rst_n(rst_n),
    .dutyCycle(dutyCycle),
    .pwm_out(pwm_out)
);

// Clock generation (10ns period → 100MHz)
always #5 clk = ~clk;

initial begin
    $display("Starting PWM Testbench...");

    $dumpfile("dump.vcd"); // Dump waveforms to a VCD file for viewing
    $dumpvars(0, tb_pwm);
    
    clk = 0;
    rst_n = 0;
    dutyCycle = 8'd0;

    // Apply reset
    #20;
    rst_n = 1;

    // 25% duty cycle
    dutyCycle = 8'd160;     // 64/256 = 25%
    #9000;



    $display("Simulation Finished.");
    $finish;
end

// Optional monitor
initial begin
    $monitor("Time=%0t | Duty=%d | PWM=%b", 
              $time, dutyCycle, pwm_out);
end

endmodule

dump.vcd
$date
	Mon Mar 23 22:44:10 2026
$end
$version
	Icarus Verilog
$end
$timescale
	1ps
$end
$scope module tb_pwm $end
$var wire 1 ! pwm_out $end
$var reg 1 " clk $end
$var reg 8 # dutyCycle [7:0] $end
$var reg 1 $ rst_n $end
$scope module uut $end
$var wire 1 " clk $end
$var wire 8 % dutyCycle [7:0] $end
$var wire 1 $ rst_n $end
$var wire 1 ! pwm_out $end
$var wire 8 & next_counter [7:0] $end
$var wire 1 ' cout_dummy $end
$var wire 8 ( counter [7:0] $end
$var wire 1 ) L $end
$var wire 1 * G $end
$var wire 1 + Eq $end
$scope module adder_inst $end
$var wire 8 , b [7:0] $end
$var wire 1 - cin $end
$var wire 8 . sum [7:0] $end
$var wire 1 ' cout $end
$var wire 9 / c [8:0] $end
$var wire 8 0 a [7:0] $end
$scope begin gen_adders[0] $end
$var parameter 2 1 i $end
$scope module fa $end
$var wire 1 2 a $end
$var wire 1 3 b $end
$var wire 1 4 cin $end
$var wire 1 5 cout $end
$var wire 1 6 sum $end
$var wire 1 7 s1 $end
$var wire 1 8 c2 $end
$var wire 1 9 c1 $end
$scope module ha1 $end
$var wire 1 2 a $end
$var wire 1 3 b $end
$var wire 1 9 carry $end
$var wire 1 7 sum $end
$upscope $end
$scope module ha2 $end
$var wire 1 7 a $end
$var wire 1 4 b $end
$var wire 1 8 carry $end
$var wire 1 6 sum $end
$upscope $end
$upscope $end
$upscope $end
$scope begin gen_adders[1] $end
$var parameter 2 : i $end
$scope module fa $end
$var wire 1 ; a $end
$var wire 1 < b $end
$var wire 1 = cin $end
$var wire 1 > cout $end
$var wire 1 ? sum $end
$var wire 1 @ s1 $end
$var wire 1 A c2 $end
$var wire 1 B c1 $end
$scope module ha1 $end
$var wire 1 ; a $end
$var wire 1 < b $end
$var wire 1 B carry $end
$var wire 1 @ sum $end
$upscope $end
$scope module ha2 $end
$var wire 1 @ a $end
$var wire 1 = b $end
$var wire 1 A carry $end
$var wire 1 ? sum $end
$upscope $end
$upscope $end
$upscope $end
$scope begin gen_adders[2] $end
$var parameter 3 C i $end
$scope module fa $end
$var wire 1 D a $end
$var wire 1 E b $end
$var wire 1 F cin $end
$var wire 1 G cout $end
$var wire 1 H sum $end
$var wire 1 I s1 $end
$var wire 1 J c2 $end
$var wire 1 K c1 $end
$scope module ha1 $end
$var wire 1 D a $end
$var wire 1 E b $end
$var wire 1 K carry $end
$var wire 1 I sum $end
$upscope $end
$scope module ha2 $end
$var wire 1 I a $end
$var wire 1 F b $end
$var wire 1 J carry $end
$var wire 1 H sum $end
$upscope $end
$upscope $end
$upscope $end
$scope begin gen_adders[3] $end
$var parameter 3 L i $end
$scope module fa $end
$var wire 1 M a $end
$var wire 1 N b $end
$var wire 1 O cin $end
$var wire 1 P cout $end
$var wire 1 Q sum $end
$var wire 1 R s1 $end
$var wire 1 S c2 $end
$var wire 1 T c1 $end
$scope module ha1 $end
$var wire 1 M a $end
$var wire 1 N b $end
$var wire 1 T carry $end
$var wire 1 R sum $end
$upscope $end
$scope module ha2 $end
$var wire 1 R a $end
$var wire 1 O b $end
$var wire 1 S carry $end
$var wire 1 Q sum $end
$upscope $end
$upscope $end
$upscope $end
$scope begin gen_adders[4] $end
$var parameter 4 U i $end
$scope module fa $end
$var wire 1 V a $end
$var wire 1 W b $end
$var wire 1 X cin $end
$var wire 1 Y cout $end
$var wire 1 Z sum $end
$var wire 1 [ s1 $end
$var wire 1 \ c2 $end
$var wire 1 ] c1 $end
$scope module ha1 $end
$var wire 1 V a $end
$var wire 1 W b $end
$var wire 1 ] carry $end
$var wire 1 [ sum $end
$upscope $end
$scope module ha2 $end
$var wire 1 [ a $end
$var wire 1 X b $end
$var wire 1 \ carry $end
$var wire 1 Z sum $end
$upscope $end
$upscope $end
$upscope $end
$scope begin gen_adders[5] $end
$var parameter 4 ^ i $end
$scope module fa $end
$var wire 1 _ a $end
$var wire 1 ` b $end
$var wire 1 a cin $end
$var wire 1 b cout $end
$var wire 1 c sum $end
$var wire 1 d s1 $end
$var wire 1 e c2 $end
$var wire 1 f c1 $end
$scope module ha1 $end
$var wire 1 _ a $end
$var wire 1 ` b $end
$var wire 1 f carry $end
$var wire 1 d sum $end
$upscope $end
$scope module ha2 $end
$var wire 1 d a $end
$var wire 1 a b $end
$var wire 1 e carry $end
$var wire 1 c sum $end
$upscope $end
$upscope $end
$upscope $end
$scope begin gen_adders[6] $end
$var parameter 4 g i $end
$scope module fa $end
$var wire 1 h a $end
$var wire 1 i b $end
$var wire 1 j cin $end
$var wire 1 k cout $end
$var wire 1 l sum $end
$var wire 1 m s1 $end
$var wire 1 n c2 $end
$var wire 1 o c1 $end
$scope module ha1 $end
$var wire 1 h a $end
$var wire 1 i b $end
$var wire 1 o carry $end
$var wire 1 m sum $end
$upscope $end
$scope module ha2 $end
$var wire 1 m a $end
$var wire 1 j b $end
$var wire 1 n carry $end
$var wire 1 l sum $end
$upscope $end
$upscope $end
$upscope $end
$scope begin gen_adders[7] $end
$var parameter 4 p i $end
$scope module fa $end
$var wire 1 q a $end
$var wire 1 r b $end
$var wire 1 s cin $end
$var wire 1 t cout $end
$var wire 1 u sum $end
$var wire 1 v s1 $end
$var wire 1 w c2 $end
$var wire 1 x c1 $end
$scope module ha1 $end
$var wire 1 q a $end
$var wire 1 r b $end
$var wire 1 x carry $end
$var wire 1 v sum $end
$upscope $end
$scope module ha2 $end
$var wire 1 v a $end
$var wire 1 s b $end
$var wire 1 w carry $end
$var wire 1 u sum $end
$upscope $end
$upscope $end
$upscope $end
$upscope $end
$scope module comp_inst $end
$var wire 8 y B [7:0] $end
$var wire 1 * G $end
$var wire 1 ) L $end
$var wire 8 z Lw [7:0] $end
$var wire 8 { Gw [7:0] $end
$var wire 8 | Eqw [7:0] $end
$var wire 1 + Eq $end
$var wire 8 } A [7:0] $end
$scope module c0 $end
$var wire 1 ~ Eq $end
$var wire 1 !" G $end
$var wire 1 "" L $end
$var wire 1 #" a $end
$var wire 1 $" b $end
$upscope $end
$scope module c1 $end
$var wire 1 %" Eq $end
$var wire 1 &" G $end
$var wire 1 '" L $end
$var wire 1 (" a $end
$var wire 1 )" b $end
$upscope $end
$scope module c2 $end
$var wire 1 *" Eq $end
$var wire 1 +" G $end
$var wire 1 ," L $end
$var wire 1 -" a $end
$var wire 1 ." b $end
$upscope $end
$scope module c3 $end
$var wire 1 /" Eq $end
$var wire 1 0" G $end
$var wire 1 1" L $end
$var wire 1 2" a $end
$var wire 1 3" b $end
$upscope $end
$scope module c4 $end
$var wire 1 4" Eq $end
$var wire 1 5" G $end
$var wire 1 6" L $end
$var wire 1 7" a $end
$var wire 1 8" b $end
$upscope $end
$scope module c5 $end
$var wire 1 9" Eq $end
$var wire 1 :" G $end
$var wire 1 ;" L $end
$var wire 1 <" a $end
$var wire 1 =" b $end
$upscope $end
$scope module c6 $end
$var wire 1 >" Eq $end
$var wire 1 ?" G $end
$var wire 1 @" L $end
$var wire 1 A" a $end
$var wire 1 B" b $end
$upscope $end
$scope module c7 $end
$var wire 1 C" Eq $end
$var wire 1 D" G $end
$var wire 1 E" L $end
$var wire 1 F" a $end
$var wire 1 G" b $end
$upscope $end
$upscope $end
$scope module counter_reg $end
$var wire 1 " clk $end
$var wire 8 H" d [7:0] $end
$var wire 1 $ rst_n $end
$var wire 8 I" q [7:0] $end
$scope begin dff_array[0] $end
$var parameter 2 J" i $end
$scope module dff_inst $end
$var wire 1 " clk $end
$var wire 1 K" d $end
$var wire 1 $ rst_n $end
$var reg 1 L" q $end
$upscope $end
$upscope $end
$scope begin dff_array[1] $end
$var parameter 2 M" i $end
$scope module dff_inst $end
$var wire 1 " clk $end
$var wire 1 N" d $end
$var wire 1 $ rst_n $end
$var reg 1 O" q $end
$upscope $end
$upscope $end
$scope begin dff_array[2] $end
$var parameter 3 P" i $end
$scope module dff_inst $end
$var wire 1 " clk $end
$var wire 1 Q" d $end
$var wire 1 $ rst_n $end
$var reg 1 R" q $end
$upscope $end
$upscope $end
$scope begin dff_array[3] $end
$var parameter 3 S" i $end
$scope module dff_inst $end
$var wire 1 " clk $end
$var wire 1 T" d $end
$var wire 1 $ rst_n $end
$var reg 1 U" q $end
$upscope $end
$upscope $end
$scope begin dff_array[4] $end
$var parameter 4 V" i $end
$scope module dff_inst $end
$var wire 1 " clk $end
$var wire 1 W" d $end
$var wire 1 $ rst_n $end
$var reg 1 X" q $end
$upscope $end
$upscope $end
$scope begin dff_array[5] $end
$var parameter 4 Y" i $end
$scope module dff_inst $end
$var wire 1 " clk $end
$var wire 1 Z" d $end
$var wire 1 $ rst_n $end
$var reg 1 [" q $end
$upscope $end
$upscope $end
$scope begin dff_array[6] $end
$var parameter 4 \" i $end
$scope module dff_inst $end
$var wire 1 " clk $end
$var wire 1 ]" d $end
$var wire 1 $ rst_n $end
$var reg 1 ^" q $end
$upscope $end
$upscope $end
$scope begin dff_array[7] $end
$var parameter 4 _" i $end
$scope module dff_inst $end
$var wire 1 " clk $end
$var wire 1 `" d $end
$var wire 1 $ rst_n $end
$var reg 1 a" q $end
$upscope $end
$upscope $end
$upscope $end
$scope module pwm_mux $end
$var wire 1 b" a $end
$var wire 1 c" b $end
$var wire 1 ) s $end
$var wire 1 ! y $end
$upscope $end
$upscope $end
$upscope $end
$enddefinitions $end
$comment Show the parameter values. $end
$dumpall
b111 _"
b110 \"
b101 Y"
b100 V"
b11 S"
b10 P"
b1 M"
b0 J"
b111 p
b110 g
b101 ^
b100 U
b11 L
b10 C
b1 :
b0 1
$end
#0
$dumpvars
1c"
0b"
0a"
0`"
0^"
0]"
0["
0Z"
0X"
0W"
0U"
0T"
0R"
0Q"
0O"
0N"
0L"
1K"
b0 I"
b1 H"
0G"
0F"
0E"
0D"
1C"
0B"
0A"
0@"
0?"
1>"
0="
0<"
0;"
0:"
19"
08"
07"
06"
05"
14"
03"
02"
01"
00"
1/"
0."
0-"
0,"
0+"
1*"
0)"
0("
0'"
0&"
1%"
0$"
0#"
0""
0!"
1~
b0 }
b11111111 |
b0 {
b0 z
b0 y
0x
0w
0v
0u
0t
0s
0r
0q
0o
0n
0m
0l
0k
0j
0i
0h
0f
0e
0d
0c
0b
0a
0`
0_
0]
0\
0[
0Z
0Y
0X
0W
0V
0T
0S
0R
0Q
0P
0O
0N
0M
0K
0J
0I
0H
0G
0F
0E
0D
0B
0A
0@
0?
0>
0=
0<
0;
09
08
17
16
05
04
13
02
b0 0
b0 /
b1 .
0-
b1 ,
1+
0*
0)
b0 (
0'
b1 &
b0 %
0$
b0 #
0"
0!
$end
#5000
1"
#10000
0"
#15000
1"
#20000
1!
1)
09"
0+
b1011111 |
0C"
1;"
b10100000 z
1E"
1="
1G"
0"
b10100000 #
b10100000 %
b10100000 y
1$
#25000
1N"
1?
0K"
1=
b1011110 |
0~
b10 &
b10 .
b10 H"
06
b10 /
15
b1 {
1!"
07
19
1#"
12
b1 (
b1 0
b1 }
b1 I"
1L"
1"
#30000
0"
#35000
0Q"
0H
0F
1K"
0=
1N"
0>
1~
16
b0 /
05
b1011101 |
0%"
b11 &
b11 .
b11 H"
1?
0A
0!"
17
09
b10 {
1&"
1@
0#"
02
1("
1;
0L"
b10 (
b10 0
b10 }
b10 I"
1O"
1"
#40000
0"
#45000
1Q"
1H
1F
0N"
1>
0?
1A
0K"
1=
b1011100 |
0~
b100 &
b100 .
b100 H"
06
b110 /
15
b11 {
1!"
07
19
1#"
12
b11 (
b11 0
b11 }
b11 I"
1L"
1"
#50000
0"
#55000
0T"
0Q
0F
0O
1K"
0=
0N"
0>
1Q"
0G
1~
16
b0 /
05
1%"
0?
0A
b1011011 |
0*"
b101 &
b101 .
b101 H"
1H
0J
0!"
17
09
0&"
0@
b100 {
1+"
1I
0#"
02
0("
0;
1-"
1D
0L"
0O"
b100 (
b100 0
b100 }
b100 I"
1R"
1"
#60000
0"
#65000
1N"
1?
0K"
1=
b1011010 |
0~
b110 &
b110 .
b110 H"
06
b10 /
15
b101 {
1!"
07
19
1#"
12
b101 (
b101 0
b101 }
b101 I"
1L"
1"
#70000
0"
#75000
0T"
0Q
0O
1Q"
0G
1H
0J
0F
1K"
0=
1N"
0>
1~
16
b0 /
05
b1011001 |
0%"
b111 &
b111 .
b111 H"
1?
0A
0!"
17
09
b110 {
1&"
1@
0#"
02
1("
1;
0L"
b110 (
b110 0
b110 }
b110 I"
1O"
1"
#80000
0"
#85000
1T"
1Q
1O
0Q"
1G
0H
1J
1F
0N"
1>
0?
1A
0K"
1=
b1011000 |
0~
b1000 &
b1000 .
b1000 H"
06
b1110 /
15
b111 {
1!"
07
19
1#"
12
b111 (
b111 0
b111 }
b111 I"
1L"
1"
#90000
0"
#95000
0W"
0Z
0F
0O
0X
1K"
0=
0N"
0>
0Q"
0G
1T"
0P
1~
16
b0 /
05
1%"
0?
0A
1*"
0H
0J
b1010111 |
0/"
b1001 &
b1001 .
b1001 H"
1Q
0S
0!"
17
09
0&"
0@
0+"
0I
b1000 {
10"
1R
0#"
02
0("
0;
0-"
0D
12"
1M
0L"
0O"
0R"
b1000 (
b1000 0
b1000 }
b1000 I"
1U"
1"
#100000
0"
#105000
1N"
1?
0K"
1=
b1010110 |
0~
b1010 &
b1010 .
b1010 H"
06
b10 /
15
b1001 {
1!"
07
19
1#"
12
b1001 (
b1001 0
b1001 }
b1001 I"
1L"
1"
#110000
0"
#115000
0Q"
0H
0F
1K"
0=
1N"
0>
1~
16
b0 /
05
b1010101 |
0%"
b1011 &
b1011 .
b1011 H"
1?
0A
0!"
17
09
b1010 {
1&"
1@
0#"
02
1("
1;
0L"
b1010 (
b1010 0
b1010 }
b1010 I"
1O"
1"
#120000
0"
#125000
1Q"
1H
1F
0N"
1>
0?
1A
0K"
1=
b1010100 |
0~
b1100 &
b1100 .
b1100 H"
06
b110 /
15
b1011 {
1!"
07
19
1#"
12
b1011 (
b1011 0
b1011 }
b1011 I"
1L"
1"
#130000
0"
#135000
0W"
0Z
0X
1T"
0P
1Q
0S
0F
0O
1K"
0=
0N"
0>
1Q"
0G
1~
16
b0 /
05
1%"
0?
0A
b1010011 |
0*"
b1101 &
b1101 .
b1101 H"
1H
0J
0!"
17
09
0&"
0@
b1100 {
1+"
1I
0#"
02
0("
0;
1-"
1D
0L"
0O"
b1100 (
b1100 0
b1100 }
b1100 I"
1R"
1"
#140000
0"
#145000
1N"
1?
0K"
1=
b1010010 |
0~
b1110 &
b1110 .
b1110 H"
06
b10 /
15
b1101 {
1!"
07
19
1#"
12
b1101 (
b1101 0
b1101 }
b1101 I"
1L"
1"
#150000
0"
#155000
0W"
0Z
0X
1T"
0P
1Q
0S
0O
1Q"
0G
1H
0J
0F
1K"
0=
1N"
0>
1~
16
b0 /
05
b1010001 |
0%"
b1111 &
b1111 .
b1111 H"
1?
0A
0!"
17
09
b1110 {
1&"
1@
0#"
02
1("
1;
0L"
b1110 (
b1110 0
b1110 }
b1110 I"
1O"
1"
#160000
0"
#165000
1W"
1Z
1X
0T"
1P
0Q
1S
1O
0Q"
1G
0H
1J
1F
0N"
1>
0?
1A
0K"
1=
b1010000 |
0~
b10000 &
b10000 .
b10000 H"
06
b11110 /
15
b1111 {
1!"
07
19
1#"
12
b1111 (
b1111 0
b1111 }
b1111 I"
1L"
1"
#170000
0"
#175000
0Z"
0c
0F
0O
0X
0a
1K"
0=
0N"
0>
0Q"
0G
0T"
0P
1W"
0Y
1~
16
b0 /
05
1%"
0?
0A
1*"
0H
0J
1/"
0Q
0S
b1001111 |
04"
b10001 &
b10001 .
b10001 H"
1Z
0\
0!"
17
09
0&"
0@
0+"
0I
00"
0R
b10000 {
15"
1[
0#"
02
0("
0;
0-"
0D
02"
0M
17"
1V
0L"
0O"
0R"
0U"
b10000 (
b10000 0
b10000 }
b10000 I"
1X"
1"
#180000
0"
#185000
1N"
1?
0K"
1=
b1001110 |
0~
b10010 &
b10010 .
b10010 H"
06
b10 /
15
b10001 {
1!"
07
19
1#"
12
b10001 (
b10001 0
b10001 }
b10001 I"
1L"
1"
#190000
0"
#195000
0Q"
0H
0F
1K"
0=
1N"
0>
1~
16
b0 /
05
b1001101 |
0%"
b10011 &
b10011 .
b10011 H"
1?
0A
0!"
17
09
b10010 {
1&"
1@
0#"
02
1("
1;
0L"
b10010 (
b10010 0
b10010 }
b10010 I"
1O"
1"
#200000
0"
#205000
1Q"
1H
1F
0N"
1>
0?
1A
0K"
1=
b1001100 |
0~
b10100 &
b10100 .
b10100 H"
06
b110 /
15
b10011 {
1!"
07
19
1#"
12
b10011 (
b10011 0
b10011 }
b10011 I"
1L"
1"
#210000
0"
#215000
0T"
0Q
0F
0O
1K"
0=
0N"
0>
1Q"
0G
1~
16
b0 /
05
1%"
0?
0A
b1001011 |
0*"
b10101 &
b10101 .
b10101 H"
1H
0J
0!"
17
09
0&"
0@
b10100 {
1+"
1I
0#"
02
0("
0;
1-"
1D
0L"
0O"
b10100 (
b10100 0
b10100 }
b10100 I"
1R"
1"
#220000
0"
#225000
1N"
1?
0K"
1=
b1001010 |
0~
b10110 &
b10110 .
b10110 H"
06
b10 /
15
b10101 {
1!"
07
19
1#"
12
b10101 (
b10101 0
b10101 }
b10101 I"
1L"
1"
#230000
0"
#235000
0T"
0Q
0O
1Q"
0G
1H
0J
0F
1K"
0=
1N"
0>
1~
16
b0 /
05
b1001001 |
0%"
b10111 &
b10111 .
b10111 H"
1?
0A
0!"
17
09
b10110 {
1&"
1@
0#"
02
1("
1;
0L"
b10110 (
b10110 0
b10110 }
b10110 I"
1O"
1"
#240000
0"
#245000
1T"
1Q
1O
0Q"
1G
0H
1J
1F
0N"
1>
0?
1A
0K"
1=
b1001000 |
0~
b11000 &
b11000 .
b11000 H"
06
b1110 /
15
b10111 {
1!"
07
19
1#"
12
b10111 (
b10111 0
b10111 }
b10111 I"
1L"
1"
#250000
0"
#255000
0Z"
0c
0a
1W"
0Y
1Z
0\
0F
0O
0X
1K"
0=
0N"
0>
0Q"
0G
1T"
0P
1~
16
b0 /
05
1%"
0?
0A
1*"
0H
0J
b1000111 |
0/"
b11001 &
b11001 .
b11001 H"
1Q
0S
0!"
17
09
0&"
0@
0+"
0I
b11000 {
10"
1R
0#"
02
0("
0;
0-"
0D
12"
1M
0L"
0O"
0R"
b11000 (
b11000 0
b11000 }
b11000 I"
1U"
1"
#260000
0"
#265000
1N"
1?
0K"
1=
b1000110 |
0~
b11010 &
b11010 .
b11010 H"
06
b10 /
15
b11001 {
1!"
07
19
1#"
12
b11001 (
b11001 0
b11001 }
b11001 I"
1L"
1"
#270000
0"
#275000
0Q"
0H
0F
1K"
0=
1N"
0>
1~
16
b0 /
05
b1000101 |
0%"
b11011 &
b11011 .
b11011 H"
1?
0A
0!"
17
09
b11010 {
1&"
1@
0#"
02
1("
1;
0L"
b11010 (
b11010 0
b11010 }
b11010 I"
1O"
1"
#280000
0"
#285000
1Q"
1H
1F
0N"
1>
0?
1A
0K"
1=
b1000100 |
0~
b11100 &
b11100 .
b11100 H"
06
b110 /
15
b11011 {
1!"
07
19
1#"
12
b11011 (
b11011 0
b11011 }
b11011 I"
1L"
1"
#290000
0"
#295000
0Z"
0c
0a
1W"
0Y
1Z
0\
0X
1T"
0P
1Q
0S
0F
0O
1K"
0=
0N"
0>
1Q"
0G
1~
16
b0 /
05
1%"
0?
0A
b1000011 |
0*"
b11101 &
b11101 .
b11101 H"
1H
0J
0!"
17
09
0&"
0@
b11100 {
1+"
1I
0#"
02
0("
0;
1-"
1D
0L"
0O"
b11100 (
b11100 0
b11100 }
b11100 I"
1R"
1"
#300000
0"
#305000
1N"
1?
0K"
1=
b1000010 |
0~
b11110 &
b11110 .
b11110 H"
06
b10 /
15
b11101 {
1!"
07
19
1#"
12
b11101 (
b11101 0
b11101 }
b11101 I"
1L"
1"
#310000
0"
#315000
0Z"
0c
0a
1W"
0Y
1Z
0\
0X
1T"
0P
1Q
0S
0O
1Q"
0G
1H
0J
0F
1K"
0=
1N"
0>
1~
16
b0 /
05
b1000001 |
0%"
b11111 &
b11111 .
b11111 H"
1?
0A
0!"
17
09
b11110 {
1&"
1@
0#"
02
1("
1;
0L"
b11110 (
b11110 0
b11110 }
b11110 I"
1O"
1"
#320000
0"
#325000
1Z"
1c
1a
0W"
1Y
0Z
1\
1X
0T"
1P
0Q
1S
1O
0Q"
1G
0H
1J
1F
0N"
1>
0?
1A
0K"
1=
b1000000 |
0~
b100000 &
b100000 .
b100000 H"
06
b111110 /
15
b11111 {
1!"
07
19
1#"
12
b11111 (
b11111 0
b11111 }
b11111 I"
1L"
1"
#330000
0"
#335000
0]"
0l
0F
0O
0X
0a
0j
1K"
0=
0N"
0>
0Q"
0G
0T"
0P
0W"
0Y
1Z"
0b
1~
16
b0 /
05
1%"
0?
0A
1*"
0H
0J
1/"
0Q
0S
14"
0Z
0\
b10000000 z
0;"
b1111111 |
19"
b100001 &
b100001 .
b100001 H"
1c
0e
0!"
17
09
0&"
0@
0+"
0I
00"
0R
b0 {
05"
0[
1d
0#"
02
0("
0;
0-"
0D
02"
0M
07"
0V
1<"
1_
0L"
0O"
0R"
0U"
0X"
b100000 (
b100000 0
b100000 }
b100000 I"
1["
1"
#340000
0"
#345000
1N"
1?
0K"
1=
b1111110 |
0~
b100010 &
b100010 .
b100010 H"
06
b10 /
15
b1 {
1!"
07
19
1#"
12
b100001 (
b100001 0
b100001 }
b100001 I"
1L"
1"
#350000
0"
#355000
0Q"
0H
0F
1K"
0=
1N"
0>
1~
16
b0 /
05
b1111101 |
0%"
b100011 &
b100011 .
b100011 H"
1?
0A
0!"
17
09
b10 {
1&"
1@
0#"
02
1("
1;
0L"
b100010 (
b100010 0
b100010 }
b100010 I"
1O"
1"
#360000
0"
#365000
1Q"
1H
1F
0N"
1>
0?
1A
0K"
1=
b1111100 |
0~
b100100 &
b100100 .
b100100 H"
06
b110 /
15
b11 {
1!"
07
19
1#"
12
b100011 (
b100011 0
b100011 }
b100011 I"
1L"
1"
#370000
0"
#375000
0T"
0Q
0F
0O
1K"
0=
0N"
0>
1Q"
0G
1~
16
b0 /
05
1%"
0?
0A
b1111011 |
0*"
b100101 &
b100101 .
b100101 H"
1H
0J
0!"
17
09
0&"
0@
b100 {
1+"
1I
0#"
02
0("
0;
1-"
1D
0L"
0O"
b100100 (
b100100 0
b100100 }
b100100 I"
1R"
1"
#380000
0"
#385000
1N"
1?
0K"
1=
b1111010 |
0~
b100110 &
b100110 .
b100110 H"
06
b10 /
15
b101 {
1!"
07
19
1#"
12
b100101 (
b100101 0
b100101 }
b100101 I"
1L"
1"
#390000
0"
#395000
0T"
0Q
0O
1Q"
0G
1H
0J
0F
1K"
0=
1N"
0>
1~
16
b0 /
05
b1111001 |
0%"
b100111 &
b100111 .
b100111 H"
1?
0A
0!"
17
09
b110 {
1&"
1@
0#"
02
1("
1;
0L"
b100110 (
b100110 0
b100110 }
b100110 I"
1O"
1"
#400000
0"
#405000
1T"
1Q
1O
0Q"
1G
0H
1J
1F
0N"
1>
0?
1A
0K"
1=
b1111000 |
0~
b101000 &
b101000 .
b101000 H"
06
b1110 /
15
b111 {
1!"
07
19
1#"
12
b100111 (
b100111 0
b100111 }
b100111 I"
1L"
1"
#410000
0"
#415000
0W"
0Z
0F
0O
0X
1K"
0=
0N"
0>
0Q"
0G
1T"
0P
1~
16
b0 /
05
1%"
0?
0A
1*"
0H
0J
b1110111 |
0/"
b101001 &
b101001 .
b101001 H"
1Q
0S
0!"
17
09
0&"
0@
0+"
0I
b1000 {
10"
1R
0#"
02
0("
0;
0-"
0D
12"
1M
0L"
0O"
0R"
b101000 (
b101000 0
b101000 }
b101000 I"
1U"
1"
#420000
0"
#425000
1N"
1?
0K"
1=
b1110110 |
0~
b101010 &
b101010 .
b101010 H"
06
b10 /
15
b1001 {
1!"
07
19
1#"
12
b101001 (
b101001 0
b101001 }
b101001 I"
1L"
1"
#430000
0"
