dff_8bit.v
module dff_1bit (
    output reg q,
    input wire d,
    input wire clk,
    input wire rst_n
);

    always @(posedge clk or negedge rst_n) begin
        if (!rst_n) begin
            q <= 1'b0; // Active-low reset
        end else begin
            q <= d;    // On positive clock edge, q gets the value of d
        end
    end

endmodule

module dff_8bit (
    output wire [7:0] q,
    input  wire [7:0] d,
    input  wire clk,
    input  wire rst_n
);

genvar i;
generate
    for (i = 0; i < 8; i = i + 1) begin : dff_array
        dff_1bit dff_inst (
            .q(q[i]),
            .d(d[i]),
            .clk(clk),
            .rst_n(rst_n)
        );
    end
endgenerate

endmodule

tb_dff_8bit.v
`timescale 1ns/1ps

module dff_8bit_tb;

reg  [7:0] d;
reg  clk;
reg  rst_n;
wire [7:0] q;

// Instantiate DUT
dff_8bit uut (
    .q(q),
    .d(d),
    .clk(clk),
    .rst_n(rst_n)
);

// Clock generation (10ns period)
always #5 clk = ~clk;

initial begin
    $dumpfile("dump_dff_8bit.vcd");
    $dumpvars(0, dff_8bit_tb);

    $display("Starting 8-bit DFF Testbench");
    $display("--------------------------------");

    clk = 0;
    rst_n = 0;
    d = 8'b00000000;

    // Apply reset
    #12;
    rst_n = 1;   // Release reset

    // Apply test vectors
    #10 d = 8'b10101010;
    #10 check_output();

    #10 d = 8'b11110000;
    #10 check_output();

    #10 d = 8'b00001111;
    #10 check_output();

    #10 d = 8'b11111111;
    #10 check_output();

    #10 d = 8'b00000000;
    #10 check_output();

    $display("--------------------------------");
    $display("Testing Completed");
    $finish;
end


// Task to verify output
task check_output;
begin
    if (q === d)
        $display("PASS  Time=%0t  D=%b  Q=%b", $time, d, q);
    else
        $display("FAIL  Time=%0t  D=%b  Q=%b", $time, d, q);
end
endtask

endmodule

dump_dff_8bit.vcd
$date
	Mon Mar 23 22:37:43 2026
$end
$version
	Icarus Verilog
$end
$timescale
	1ps
$end
$scope module dff_8bit_tb $end
$var wire 8 ! q [7:0] $end
$var reg 1 " clk $end
$var reg 8 # d [7:0] $end
$var reg 1 $ rst_n $end
$scope module uut $end
$var wire 1 " clk $end
$var wire 8 % d [7:0] $end
$var wire 1 $ rst_n $end
$var wire 8 & q [7:0] $end
$scope begin dff_array[0] $end
$var parameter 2 ' i $end
$scope module dff_inst $end
$var wire 1 " clk $end
$var wire 1 ( d $end
$var wire 1 $ rst_n $end
$var reg 1 ) q $end
$upscope $end
$upscope $end
$scope begin dff_array[1] $end
$var parameter 2 * i $end
$scope module dff_inst $end
$var wire 1 " clk $end
$var wire 1 + d $end
$var wire 1 $ rst_n $end
$var reg 1 , q $end
$upscope $end
$upscope $end
$scope begin dff_array[2] $end
$var parameter 3 - i $end
$scope module dff_inst $end
$var wire 1 " clk $end
$var wire 1 . d $end
$var wire 1 $ rst_n $end
$var reg 1 / q $end
$upscope $end
$upscope $end
$scope begin dff_array[3] $end
$var parameter 3 0 i $end
$scope module dff_inst $end
$var wire 1 " clk $end
$var wire 1 1 d $end
$var wire 1 $ rst_n $end
$var reg 1 2 q $end
$upscope $end
$upscope $end
$scope begin dff_array[4] $end
$var parameter 4 3 i $end
$scope module dff_inst $end
$var wire 1 " clk $end
$var wire 1 4 d $end
$var wire 1 $ rst_n $end
$var reg 1 5 q $end
$upscope $end
$upscope $end
$scope begin dff_array[5] $end
$var parameter 4 6 i $end
$scope module dff_inst $end
$var wire 1 " clk $end
$var wire 1 7 d $end
$var wire 1 $ rst_n $end
$var reg 1 8 q $end
$upscope $end
$upscope $end
$scope begin dff_array[6] $end
$var parameter 4 9 i $end
$scope module dff_inst $end
$var wire 1 " clk $end
$var wire 1 : d $end
$var wire 1 $ rst_n $end
$var reg 1 ; q $end
$upscope $end
$upscope $end
$scope begin dff_array[7] $end
$var parameter 4 < i $end
$scope module dff_inst $end
$var wire 1 " clk $end
$var wire 1 = d $end
$var wire 1 $ rst_n $end
$var reg 1 > q $end
$upscope $end
$upscope $end
$upscope $end
$scope task check_output $end
$upscope $end
$upscope $end
$enddefinitions $end
$comment Show the parameter values. $end
$dumpall
b111 <
b110 9
b101 6
b100 3
b11 0
b10 -
b1 *
b0 '
$end
#0
$dumpvars
0>
0=
0;
0:
08
07
05
04
02
01
0/
0.
0,
0+
0)
0(
b0 &
b0 %
0$
b0 #
0"
b0 !
$end
#5000
1"
#10000
0"
#12000
1$
#15000
1"
#20000
0"
#22000
1+
11
17
1=
b10101010 #
b10101010 %
#25000
1>
18
12
b10101010 !
b10101010 &
1,
1"
#30000
0"
#35000
1"
#40000
0"
#42000
0+
01
14
1:
b11110000 #
b11110000 %
#45000
1;
15
02
b11110000 !
b11110000 &
0,
1"
#50000
0"
#55000
1"
#60000
0"
#62000
1(
1+
1.
11
04
07
0:
0=
b1111 #
b1111 %
#65000
0>
0;
08
05
12
1/
1,
b1111 !
b1111 &
1)
1"
#70000
0"
#75000
1"
#80000
0"
#82000
14
17
1:
1=
b11111111 #
b11111111 %
#85000
1>
1;
18
b11111111 !
b11111111 &
15
1"
#90000
0"
#95000
1"
#100000
0"
#102000
0(
0+
0.
01
04
07
0:
0=
b0 #
b0 %
#105000
0>
0;
08
05
02
0/
0,
b0 !
b0 &
0)
1"
